primus_safe_pulsekit_pytorch_launcher/__init__.py
primus_safe_pulsekit_pytorch_launcher/__main__.py
primus_safe_pulsekit_pytorch_launcher/launcher.py
primus_safe_pulsekit_pytorch_launcher-0.1.1.dist-info/METADATA
primus_safe_pulsekit_pytorch_launcher-0.1.1.dist-info/WHEEL
primus_safe_pulsekit_pytorch_launcher-0.1.1.dist-info/top_level.txt
primus_safe_pulsekit_pytorch_launcher-0.1.1.dist-info/RECORD
